ticktick_mcp/__init__.py
ticktick_mcp/authenticate.py
ticktick_mcp/cli.py
ticktick_mcp/src/__init__.py
ticktick_mcp/src/auth.py
ticktick_mcp/src/credentials.py
ticktick_mcp/src/server.py
ticktick_mcp/src/ticktick_client.py
ticktick_mcp_server-0.3.1.dist-info/METADATA
ticktick_mcp_server-0.3.1.dist-info/WHEEL
ticktick_mcp_server-0.3.1.dist-info/entry_points.txt
ticktick_mcp_server-0.3.1.dist-info/RECORD
