Metadata-Version: 2.4
Name: ticktick-mcp-server
Version: 0.3.1
Summary: Security-hardened MCP server for TickTick task management
Project-URL: Homepage, https://github.com/felores/ticktick-mcp-server
Project-URL: Repository, https://github.com/felores/ticktick-mcp-server
Project-URL: Issues, https://github.com/felores/ticktick-mcp-server/issues
Author-email: Felipe Lores <felores@users.noreply.github.com>
Maintainer-email: Felipe Lores <felores@users.noreply.github.com>
License-Expression: MIT
Keywords: ai,claude,gtd,mcp,model-context-protocol,productivity,task-management,ticktick
Classifier: Development Status :: 4 - Beta
Classifier: Intended Audience :: Developers
Classifier: License :: OSI Approved :: MIT License
Classifier: Operating System :: OS Independent
Classifier: Programming Language :: Python :: 3
Classifier: Programming Language :: Python :: 3.10
Classifier: Programming Language :: Python :: 3.11
Classifier: Programming Language :: Python :: 3.12
Classifier: Programming Language :: Python :: 3.13
Classifier: Topic :: Office/Business :: Scheduling
Classifier: Topic :: Software Development :: Libraries :: Python Modules
Requires-Python: >=3.10
Requires-Dist: mcp[cli]<2.0.0,>=1.2.0
Requires-Dist: python-dotenv<2.0.0,>=1.0.0
Requires-Dist: requests<3.0.0,>=2.30.0
